optimization/geckodriver.log
optimization/jg_opt.py
optimization/maxcovering.py
optimization/optdata.py
optimization/tmp/images/q/VN_Pareto.pdf
pisa/administrative_area.py
pisa/constants.py
pisa/facilities.py
pisa/isopolygons.py
pisa/osm_road_network.py
pisa/population.py
pisa/population_served_by_isopolygons.py
pisa/utils.py
pisa/visualisation.py
pisa_abw-2.0.2.dist-info/LICENSE
pisa_abw-2.0.2.dist-info/METADATA
pisa_abw-2.0.2.dist-info/WHEEL
pisa_abw-2.0.2.dist-info/RECORD
