Metadata-Version: 2.1
Name: pisa_abw
Version: 2.0.2
Summary: Estimate and optimize service coverage of public infrastructure facilities.
Author: EiriniK
Author-email: Eirini.Kousathana@ortec.com
Requires-Python: >=3.10,<3.11
Classifier: Programming Language :: Python :: 3
Classifier: Programming Language :: Python :: 3.10
Requires-Dist: folium (>=0.13.0,<0.14.0)
Requires-Dist: gadm (>=0.0.3,<0.0.4)
Requires-Dist: geopandas (>=1.0.1,<2.0.0)
Requires-Dist: gurobipy
Requires-Dist: hdx-python-api (>=5.9.2,<6.0.0)
Requires-Dist: highspy
Requires-Dist: ipykernel (>=6.16.2,<7.0.0)
Requires-Dist: jupyter (>=1.0.0,<2.0.0)
Requires-Dist: jupyter-utils (>=1.2.6,<2.0.0)
Requires-Dist: matplotlib (>=3.10.0,<4.0.0)
Requires-Dist: nbclient (>=0.7.2,<0.8.0)
Requires-Dist: networkx (>=2.8)
Requires-Dist: numpy (>=1.23.5,<2.0.0)
Requires-Dist: osmnx (>=2.0.1,<3.0.0)
Requires-Dist: osmxtract (>=0.0.1,<0.0.2)
Requires-Dist: pandana
Requires-Dist: plotly (>=5.22.0,<6.0.0)
Requires-Dist: pycountry (==22.3.5)
Requires-Dist: pygeos (==0.12)
Requires-Dist: pyomo (>=6.4.3,<7.0.0)
Requires-Dist: pyproj (>=3.3)
Requires-Dist: python-dotenv (>=1.1.0,<2.0.0)
Requires-Dist: rasterio (>=1.3.3,<2.0.0)
Requires-Dist: requests (>=2.28)
Requires-Dist: shapely (>=2.0.6,<3.0.0)
Requires-Dist: streamlit (>=1.15.2,<2.0.0)
Requires-Dist: streamlit-folium (>=0.20.0,<0.21.0)
Requires-Dist: streamlit-plotly-events (>=0.0.6,<0.0.7)
